Metadata-Version: 2.1
Name: gatepy
Version: 1.0.2
Summary: UNKNOWN
Home-page: https://github.com/MrNereof/gatepy/
Author: MrNereof
Author-email: mrnereof@gmail.com
License: MIT
Keywords: gate,logical gate
Platform: UNKNOWN
Classifier: Development Status :: 4 - Beta
Classifier: Intended Audience :: Other Audience
Classifier: License :: OSI Approved :: MIT License
Classifier: Operating System :: OS Independent
Classifier: Programming Language :: Python :: 3.4
Classifier: Programming Language :: Python :: 3.6
Classifier: Programming Language :: Python :: 3.7
Classifier: Programming Language :: Python :: 3.8
Classifier: Programming Language :: Python :: 3.9
Requires-Python: >=3.4
